sentinel_protobuf/__init__.py
sentinel_protobuf/__init__.pyi
sentinel_protobuf/cosmos/__init__.py
sentinel_protobuf/cosmos/__init__.pyi
sentinel_protobuf/cosmos/app/__init__.py
sentinel_protobuf/cosmos/app/__init__.pyi
sentinel_protobuf/cosmos/app/runtime/__init__.py
sentinel_protobuf/cosmos/app/runtime/__init__.pyi
sentinel_protobuf/cosmos/app/runtime/v1alpha1/__init__.py
sentinel_protobuf/cosmos/app/runtime/v1alpha1/__init__.pyi
sentinel_protobuf/cosmos/app/runtime/v1alpha1/module.proto
sentinel_protobuf/cosmos/app/runtime/v1alpha1/module_pb2.py
sentinel_protobuf/cosmos/app/runtime/v1alpha1/module_pb2.pyi
sentinel_protobuf/cosmos/app/v1alpha1/__init__.py
sentinel_protobuf/cosmos/app/v1alpha1/__init__.pyi
sentinel_protobuf/cosmos/app/v1alpha1/config.proto
sentinel_protobuf/cosmos/app/v1alpha1/config_pb2.py
sentinel_protobuf/cosmos/app/v1alpha1/config_pb2.pyi
sentinel_protobuf/cosmos/app/v1alpha1/module.proto
sentinel_protobuf/cosmos/app/v1alpha1/module_pb2.py
sentinel_protobuf/cosmos/app/v1alpha1/module_pb2.pyi
sentinel_protobuf/cosmos/app/v1alpha1/query.proto
sentinel_protobuf/cosmos/app/v1alpha1/query_pb2.py
sentinel_protobuf/cosmos/app/v1alpha1/query_pb2.pyi
sentinel_protobuf/cosmos/app/v1alpha1/query_pb2_grpc.py
sentinel_protobuf/cosmos/auth/__init__.py
sentinel_protobuf/cosmos/auth/__init__.pyi
sentinel_protobuf/cosmos/auth/module/__init__.py
sentinel_protobuf/cosmos/auth/module/__init__.pyi
sentinel_protobuf/cosmos/auth/module/v1/__init__.py
sentinel_protobuf/cosmos/auth/module/v1/__init__.pyi
sentinel_protobuf/cosmos/auth/module/v1/module.proto
sentinel_protobuf/cosmos/auth/module/v1/module_pb2.py
sentinel_protobuf/cosmos/auth/module/v1/module_pb2.pyi
sentinel_protobuf/cosmos/auth/v1beta1/__init__.py
sentinel_protobuf/cosmos/auth/v1beta1/__init__.pyi
sentinel_protobuf/cosmos/auth/v1beta1/auth.proto
sentinel_protobuf/cosmos/auth/v1beta1/genesis.proto
sentinel_protobuf/cosmos/auth/v1beta1/query.proto
sentinel_protobuf/cosmos/auth/v1beta1/tx.proto
sentinel_protobuf-0.4.0.dist-info/METADATA
sentinel_protobuf-0.4.0.dist-info/WHEEL
sentinel_protobuf-0.4.0.dist-info/RECORD
