Metadata-Version: 2.4
Name: sentinel_protobuf
Version: 0.4.0
Summary: This package contains a compiled python version of all sentinel protobuf files with their dependencies
Project-URL: Homepage, https://github.com/MathNodes/cosmospy-protobuf/
Project-URL: Bug Tracker, https://github.com/MathNodes/cosmospy-protobuf/issues
Author-email: freQniK <freQniK@mathnodes.com>
License: BSD 3-Clause License
Keywords: cosmos,cosmospy,cosmospy-protobuf,proto,protobuf,sentinel,sentinel-protobuf
Classifier: Operating System :: OS Independent
Classifier: Programming Language :: Python :: 3
Requires-Dist: protobuf
